[
  {
    "name": "Faks Cafe",
    "adress": "1308 Av. Maguire",
    "phone": 4186860808,
    "longitude": null,
    "latitude": null,
    "hours": "",
    "pictures": "",
    "type": "American",
    "minPrice": 8.0,
    "maxPrice": 35.0,
    "rating": "4.3",
    "price": "$"
  },
  {
    "name": "La Belle & La Boeuf",
    "adress": "2450 Bd Laurier",
    "phone": 5817425444,
    "longitude": null,
    "latitude": null,
    "hours": "",
    "pictures": "",
    "type": "American",
    "minPrice": 10.0,
    "maxPrice": 45.0,
    "rating": "4.2",
    "price": "$$$"
  },
  {
    "name": "Tora-Ya Ramen",
    "adress": "75 Saint-Joseph E street",
    "phone": 4187801903,
    "longitude": null,
    "latitude": null,
    "hours": "",
    "pictures": "",
    "type": "Japanese",
    "minPrice": 5.0,
    "maxPrice": 30.0,
    "rating": "4.7",
    "price": "$$$$"
  },
  {
    "name": "Albacore",
    "adress": "819 Côte d'Abraham",
    "phone": 4189146441,
    "longitude": null,
    "latitude": null,
    "hours": "",
    "pictures": "",
    "type": "Seafood",
    "minPrice": 15.0,
    "maxPrice": 55.0,
    "rating": "4.7",
    "price": "$$"
  },
  {
    "name": "Portofino Italian Bistro",
    "adress": "965 Rte de l'Église",
    "phone": 4186578888,
    "longitude": null,
    "latitude": null,
    "hours": "",
    "pictures": "",
    "type": "Italian",
    "minPrice": 9.0,
    "maxPrice": 37.0,
    "rating": "4.1",
    "price": "$$$"
  }
]
